SplIsoFind/__init__.py
SplIsoFind/plotting.py
SplIsoFind/preprocess.py
SplIsoFind/spatially_variable.py
splisofind-0.1.5.dist-info/licenses/LICENSE
splisofind-0.1.5.dist-info/METADATA
splisofind-0.1.5.dist-info/WHEEL
splisofind-0.1.5.dist-info/top_level.txt
splisofind-0.1.5.dist-info/RECORD
