Metadata-Version: 2.4
Name: SplIsoFind
Version: 0.1.5
Summary: Spatial Isoform Finder detects spatially variable isoforms in long-read spatial data
Author-email: Lieke Michielsen <lim4020@med.cornell.edu>
License: MIT License
Project-URL: Homepage, https://github.com/tilgnerlab/Spl-IsoFind
Project-URL: Source Code, https://github.com/tilgnerlab/Spl-IsoFind
Project-URL: Documentation, https://splisofind.readthedocs.io
Project-URL: Issue Tracker, https://github.com/tilgnerlab/Spl-IsoFind/issues
Keywords: spatial transcriptomics,long read,alternative splicing,isoform
Classifier: Development Status :: 5 - Production/Stable
Classifier: Intended Audience :: Science/Research
Classifier: License :: OSI Approved :: MIT License
Classifier: Programming Language :: Python :: 3.9
Classifier: Programming Language :: Python :: 3.10
Classifier: Programming Language :: Python :: 3.11
Classifier: Operating System :: POSIX :: Linux
License-File: LICENSE
Requires-Dist: pandas<2.0.0,>=1.1.2
Requires-Dist: numpy<2.0.0,>=1.19.2
Requires-Dist: scanpy>=1.10.3
Requires-Dist: scipy
Requires-Dist: statsmodels
Requires-Dist: scikit-learn
Requires-Dist: libpysal
Requires-Dist: esda
Requires-Dist: tqdm
Requires-Dist: jupyter
Requires-Dist: matplotlib
Requires-Dist: seaborn
Dynamic: license-file
